spacycake/__init__.py
spacycake/about.py
spacycake-1.0.0.dist-info/LICENSE
spacycake-1.0.0.dist-info/METADATA
spacycake-1.0.0.dist-info/WHEEL
spacycake-1.0.0.dist-info/top_level.txt
spacycake-1.0.0.dist-info/RECORD
