Metadata-Version: 2.1
Name: spacycake
Version: 1.0.0
Summary: spaCy pipeline component for adding Keyphrase Extraction.
Home-page: https://github.com/surajiyer/spacycaKE
Author: Suraj Iyer
Author-email: me@surajiyer.com
License: MIT
Platform: UNKNOWN
Requires-Dist: spacy (<3.0.0,>=2.2.1)
Requires-Dist: spacybert (>=1.0.0)
Requires-Dist: torch (>=1.4.0)
